main.py
py_example_locust-0.1.0.dist-info/METADATA
py_example_locust-0.1.0.dist-info/WHEEL
py_example_locust-0.1.0.dist-info/top_level.txt
py_example_locust-0.1.0.dist-info/RECORD
