Metadata-Version: 2.4
Name: py-example-locust
Version: 0.1.0
Summary: Hello description
Requires-Python: >=3.12
Requires-Dist: robyn>=0.64.0
Requires-Dist: ruff>=0.11.2
